bitquery/__init__.py
bitquery/bitquery.py
bitquery_python-0.1.dist-info/LICENSE
bitquery_python-0.1.dist-info/METADATA
bitquery_python-0.1.dist-info/WHEEL
bitquery_python-0.1.dist-info/top_level.txt
bitquery_python-0.1.dist-info/RECORD
