Metadata-Version: 2.1
Name: bitquery-python
Version: 0.1
Summary: A simple package to query GraphQL using Bitquery
Home-page: https://github.com/alb2001/bitquery-python
Author: alb2001
Author-email: alb2001@outlook.es
License: UNKNOWN
Project-URL: Bitquery Website, https://bitquery.io
Project-URL: Bug Tracker, https://github.com/alb2001/bitquery-python/issues
Platform: UNKNOWN
Classifier: Programming Language :: Python :: 3
Classifier: License :: OSI Approved :: GNU General Public License v3 (GPLv3)
Classifier: Operating System :: OS Independent
Requires-Python: >=3.9.2
License-File: LICENSE
